setup.cfg
setup.py
Products/__init__.py
Products.ECAutoAssessmentBox.egg-info/PKG-INFO
Products.ECAutoAssessmentBox.egg-info/SOURCES.txt
Products.ECAutoAssessmentBox.egg-info/dependency_links.txt
Products.ECAutoAssessmentBox.egg-info/entry_points.txt
Products.ECAutoAssessmentBox.egg-info/namespace_packages.txt
Products.ECAutoAssessmentBox.egg-info/not-zip-safe
Products.ECAutoAssessmentBox.egg-info/requires.txt
Products.ECAutoAssessmentBox.egg-info/top_level.txt
Products/ECAutoAssessmentBox/CHANGES.txt
Products/ECAutoAssessmentBox/LICENSE.GPL
Products/ECAutoAssessmentBox/LICENSE.TXT
Products/ECAutoAssessmentBox/README.txt
Products/ECAutoAssessmentBox/TODO.txt
Products/ECAutoAssessmentBox/__init__.py
Products/ECAutoAssessmentBox/config.py
Products/ECAutoAssessmentBox/configure.zcml
Products/ECAutoAssessmentBox/ec_tool.png
Products/ECAutoAssessmentBox/make_i18n.bat
Products/ECAutoAssessmentBox/profiles.zcml
Products/ECAutoAssessmentBox/refresh.txt
Products/ECAutoAssessmentBox/setuphandlers.py
Products/ECAutoAssessmentBox/version.txt
Products/ECAutoAssessmentBox/browser/__init__.py
Products/ECAutoAssessmentBox/browser/configure.zcml
Products/ECAutoAssessmentBox/browser/ecaab.kss
Products/ECAutoAssessmentBox/browser/ecaab_kss.py
Products/ECAutoAssessmentBox/browser/ecaabsettings.py
Products/ECAutoAssessmentBox/browser/fieldset_backend_input.pt
Products/ECAutoAssessmentBox/browser/select_backend_tests.pt
Products/ECAutoAssessmentBox/browser/vocabularies.py
Products/ECAutoAssessmentBox/browser/ecaab_images/ec_tool.png
Products/ECAutoAssessmentBox/content/DynamicDataField.py
Products/ECAutoAssessmentBox/content/DynamicDataWidget.py
Products/ECAutoAssessmentBox/content/ECAutoAssessmentBox.py
Products/ECAutoAssessmentBox/content/ECAutoAssignment.py
Products/ECAutoAssessmentBox/content/PlainTextField.py
Products/ECAutoAssessmentBox/content/__init__.py
Products/ECAutoAssessmentBox/content/interfaces.py
Products/ECAutoAssessmentBox/i18n/eduComponents-de.po
Products/ECAutoAssessmentBox/i18n/eduComponents.pot
Products/ECAutoAssessmentBox/i18n/plone-de.po
Products/ECAutoAssessmentBox/i18n/schemas.pot
Products/ECAutoAssessmentBox/profiles/default/ECAutoAssessmentBox_marker.txt
Products/ECAutoAssessmentBox/profiles/default/controlpanel.xml
Products/ECAutoAssessmentBox/profiles/default/cssregistry.xml
Products/ECAutoAssessmentBox/profiles/default/factorytool.xml
