Metadata-Version: 1.0
Name: Products.ECAutoAssessmentBox
Version: 1.4.2
Summary: Submissions for programming assignments with immediate feedback from ECSpooler.
Home-page: http://plone.org/products/ecautoassessmentbox/
Author: Mario Amelung
Author-email: mario.amelung@gmx.de
License: GPL
Platform: UNKNOWN
Classifier: Framework :: Plone
Classifier: Framework :: Zope2
Classifier: Programming Language :: Python
Classifier: Topic :: Software Development :: Libraries :: Python Modules
